prisma_ml/__init__.py
prisma_ml/dataset_information.py
prisma_ml/machine_learning.py
prisma_ml/plotting.py
prisma_ml-0.1.1.dist-info/LICENSE
prisma_ml-0.1.1.dist-info/METADATA
prisma_ml-0.1.1.dist-info/WHEEL
prisma_ml-0.1.1.dist-info/RECORD
